repository_setup/Controller.py
repository_setup/__init__.py
repository_setup/__main__.py
repository_setup/files/.gitignore
repository_setup/files/Args.py
repository_setup/files/LICENSE.md
repository_setup/files/Output.py
repository_setup/files/README.md
repository_setup/files/Util.py
repository_setup/files/__init__.py
repository_setup/files/__main__.py
repository_setup/files/setup.py
repository_setup-2.0.0.dist-info/LICENSE.md
repository_setup-2.0.0.dist-info/METADATA
repository_setup-2.0.0.dist-info/WHEEL
repository_setup-2.0.0.dist-info/entry_points.txt
repository_setup-2.0.0.dist-info/top_level.txt
repository_setup-2.0.0.dist-info/RECORD
