Metadata-Version: 2.1
Name: repository_setup
Version: 2.0.0
Summary: Creates the basic repository structure for python projects
Home-page: https://github.com/5f0ne/repository-setup
Author: 5f0
License: MIT
Classifier: Operating System :: OS Independent 
Classifier: Programming Language :: Python :: 3 
Classifier: License :: OSI Approved :: MIT License 
License-File: LICENSE.md
